bascodes/__init__.py
bascodes/__main__.py
bascodes/main.py
bascodes-0.2.3.dist-info/LICENSE
bascodes-0.2.3.dist-info/METADATA
bascodes-0.2.3.dist-info/WHEEL
bascodes-0.2.3.dist-info/entry_points.txt
bascodes-0.2.3.dist-info/top_level.txt
bascodes-0.2.3.dist-info/RECORD
