Metadata-Version: 2.1
Name: bascodes
Version: 0.2.3
Summary: Bas Steins – Terminal Card
Home-page: https://bas.codes/
Author: Bas Steins
Author-email: blog@bascodes.com
License: License :: Public Domain
Classifier: Programming Language :: Python
Classifier: Programming Language :: Python :: 3
Classifier: Operating System :: OS Independent
Classifier: License :: Public Domain
Requires-Python: >=3.6
License-File: LICENSE
